switchgrass/__init__.py
switchgrass/cli.py
switchgrass-0.1.0a1.dist-info/METADATA
switchgrass-0.1.0a1.dist-info/WHEEL
switchgrass-0.1.0a1.dist-info/licenses/LICENSE
switchgrass-0.1.0a1.dist-info/RECORD
