Metadata-Version: 2.3
Name: switchgrass
Version: 0.1.0a1
Summary: A homegrown CLI framework
Project-URL: Homepage, https://github.com/webecke/switchgrass
Project-URL: Repository, https://github.com/webecke/switchgrass
Author-email: Dallin Webecke <me@webecke.dev>
License: MIT
License-File: LICENSE
Keywords: cli,console,framework,terminal
Classifier: Development Status :: 3 - Alpha
Classifier: Intended Audience :: Developers
Classifier: Programming Language :: Python :: 3.10
Classifier: Programming Language :: Python :: 3.11
Classifier: Topic :: Software Development :: Libraries :: Python Modules
Requires-Python: >=3.10
